SNPerr/__init__.py
SNPerr/snperr.py
SNPerr-0.0.1.dist-info/LICENSE.txt
SNPerr-0.0.1.dist-info/METADATA
SNPerr-0.0.1.dist-info/WHEEL
SNPerr-0.0.1.dist-info/top_level.txt
SNPerr-0.0.1.dist-info/RECORD
