Metadata-Version: 2.1
Name: SNPerr
Version: 0.0.1
Summary: Determine read depth and variant frequency thresholds to distinguish seq errors from true SNPs.     Simulates effect of changing per-site read depth and variant frequency on accuracy of genetic diversity
Home-page: https://github.com/j3551ca/DiVirusity
Author: Jessica Caleta
Author-email: jessica.caleta@alumni.ubc.ca
License: MIT
Platform: UNKNOWN
Requires-Python: >=3.6
Requires-Dist: numpy
Requires-Dist: scipy.stats
Requires-Dist: pandas
Requires-Dist: matplotlib.pyplot
